partiell.py
partiell-0.0.2.dist-info/LICENSE
partiell-0.0.2.dist-info/METADATA
partiell-0.0.2.dist-info/WHEEL
partiell-0.0.2.dist-info/top_level.txt
partiell-0.0.2.dist-info/RECORD
