Metadata-Version: 2.1
Name: partiell
Version: 0.0.2
Summary: Partial function application with '...'
Home-page: https://github.com/jherland/partiell
Author: Johan Herland
Author-email: johan@herland.net
License: UNKNOWN
Keywords: functools partial ellipsis functional currying
Platform: UNKNOWN
Classifier: Development Status :: 2 - Pre-Alpha
Classifier: Intended Audience :: Developers
Classifier: License :: OSI Approved :: Python Software Foundation License
Classifier: Operating System :: OS Independent
Classifier: Programming Language :: Python :: 3
Classifier: Programming Language :: Python :: 3.8
Classifier: Programming Language :: Python :: 3.9
Classifier: Programming Language :: Python :: 3.10
Classifier: Topic :: Software Development :: Libraries :: Python Modules
Requires-Python: >=3.8
License-File: LICENSE
Provides-Extra: dev
Requires-Dist: black ; extra == 'dev'
Requires-Dist: flake8 ; extra == 'dev'
Requires-Dist: nox ; extra == 'dev'
Provides-Extra: dist
Requires-Dist: check-manifest ; extra == 'dist'
Requires-Dist: twine ; extra == 'dist'
Requires-Dist: wheel ; extra == 'dist'
